setup.cfg
setup.py
OutlierRemover53004/OutlierRemover.py
OutlierRemover53004/__init__.py
OutlierRemover53004.egg-info/PKG-INFO
OutlierRemover53004.egg-info/SOURCES.txt
OutlierRemover53004.egg-info/dependency_links.txt
OutlierRemover53004.egg-info/not-zip-safe
OutlierRemover53004.egg-info/requires.txt
OutlierRemover53004.egg-info/top_level.txt