Metadata-Version: 1.1
Name: OutlierRemover53004
Version: 0.1
Summary: A package for outlier removal in a CSV File
Home-page: UNKNOWN
Author: Ashutosh Rattan
Author-email: ashutosh544@gmail.com
License: MIT
Platform: UNKNOWN
Classifier: Development Status :: 3 - Alpha
Classifier: Intended Audience :: Developers
Classifier: Topic :: Software Development :: Build Tools
Classifier: License :: OSI Approved :: MIT License
Classifier: Programming Language :: Python :: 3
Classifier: Programming Language :: Python :: 3.4
Classifier: Programming Language :: Python :: 3.5
Classifier: Programming Language :: Python :: 3.6
